nyno/__init__.py
nyno/client.py
nyno-1.0.0.dist-info/METADATA
nyno-1.0.0.dist-info/WHEEL
nyno-1.0.0.dist-info/top_level.txt
nyno-1.0.0.dist-info/RECORD
