Metadata-Version: 2.4
Name: nyno
Version: 1.0.0
Summary: Python client for Nyno server (nyno.dev)
Author-email: MJ <private@example.com>
License: MIT
Project-URL: Homepage, https://github.com/empowerd-cms/nyno-python-driver
